{"cameraMode":{"drawMode":0,"name":"Shaded","section":"Shading Mode"},"sceneLighting":true,"audioPlay":false,"sceneViewState":{"m_AlwaysRefresh":false,"showFog":true,"showSkybox":true,"showFlares":true,"showImageEffects":true,"showParticleSystems":true,"showVisualEffectGraphs":true,"m_FxEnabled":true},"in2DMode":false,"pivot":{"x":0.25200897455215456,"y":-0.7568126916885376,"z":0.3681957423686981},"rotation":{"x":-0.27004510164260867,"y":0.5113920569419861,"z":-0.1667255014181137,"w":-0.799002468585968},"size":5.016740322113037,"orthographic":false}